changelog/__init__.py
changelog/changelog.py
changelog_neuropoly-1.1.0.dist-info/LICENSE
changelog_neuropoly-1.1.0.dist-info/METADATA
changelog_neuropoly-1.1.0.dist-info/WHEEL
changelog_neuropoly-1.1.0.dist-info/entry_points.txt
changelog_neuropoly-1.1.0.dist-info/top_level.txt
changelog_neuropoly-1.1.0.dist-info/RECORD
