Metadata-Version: 2.1
Name: changelog-neuropoly
Version: 1.1.0
Summary: Create a changelog file from all the merged pull requests.
Home-page: https://github.com/neuropoly/changelog
Author: NeuroPoly Lab, Polytechnique Montreal
Author-email: neuropoly@googlegroups.com
License: MIT
Platform: UNKNOWN
Classifier: Development Status :: 3 - Alpha
Classifier: License :: OSI Approved :: MIT License
Classifier: Programming Language :: Python :: 3.7
Requires-Python: >=3.5
Requires-Dist: requests
